qdarts/__init__.py
qdarts/experiment.py
qdarts/model.py
qdarts/noise_processes.py
qdarts/plotting.py
qdarts/polytope.py
qdarts/simulator.py
qdarts/tunneling_simulator.py
qdarts/util_functions.py
QDarts-1.0.4.dist-info/LICENCE.md
QDarts-1.0.4.dist-info/METADATA
QDarts-1.0.4.dist-info/WHEEL
QDarts-1.0.4.dist-info/top_level.txt
QDarts-1.0.4.dist-info/RECORD
