Metadata-Version: 2.1
Name: QDarts
Version: 1.0.4
Summary: A package for simulating realistic quantum dot arrays and their charge transitions.
Author-email: Jan Krzywda <j.a.krzywda@liacs.leidenuniv.nl>, Evert van Nieuwenburg <e.p.l.van.nieuwenburg@liacs.leidenuniv.nl>, Oswin Krause <oswin.krause@di.ku.dk>
Project-URL: Homepage, https://github.com/condensedAI/QDarts
Project-URL: Issues, https://github.com/condensedAI/QDarts
Classifier: Programming Language :: Python :: 3
Classifier: License :: OSI Approved :: MIT License
Classifier: Operating System :: OS Independent
Requires-Python: >=3.6
License-File: LICENCE.md
